{"id":"col_004","word":"advice","meaning":"lời khuyên","ipa":"/ədˈvaɪs/","pos":"noun","level":"A2","topic":"Collocations","example":{"en":"Can you give me some advice?","vi":"Bạn có thể cho tôi vài lời khuyên không?"},"audio":{"uk":"https://api.dictionaryapi.dev/media/pronunciations/en/advice-uk.mp3","us":"https://api.dictionaryapi.dev/media/pronunciations/en/advice-us.mp3"},"rel":{"synonyms":["guidance"],"antonyms":[],"collocations":["give advice","take advice"]},"meta":{"collocation_focus":true}}